quick_zip/__init__.py
quick_zip/commands/__init__.py
quick_zip/commands/audit.py
quick_zip/commands/config.py
quick_zip/commands/jobs.py
quick_zip/core/__init__.py
quick_zip/core/settings.py
quick_zip/default.toml
quick_zip/main.py
quick_zip/schema/__init__.py
quick_zip/schema/backup_job.py
quick_zip/schema/file_system.py
quick_zip/services/__init__.py
quick_zip/services/checker.py
quick_zip/services/ui.py
quick_zip/services/web.py
quick_zip/services/zipper.py
quick_zip/utils/__init__.py
quick_zip/utils/fstats.py
quick_zip-0.1.9.dist-info/entry_points.txt
quick_zip-0.1.9.dist-info/LICENSE
quick_zip-0.1.9.dist-info/WHEEL
quick_zip-0.1.9.dist-info/METADATA
quick_zip-0.1.9.dist-info/RECORD
