Metadata-Version: 2.1
Name: quick-zip
Version: 0.1.9
Summary: 
Home-page: https://hay-kot.github.io/quick-zip-cli/
License: MIT
Author: hay-kot
Author-email: hay-kot@pm.me
Requires-Python: >=3.8,<4.0
Classifier: License :: OSI Approved :: MIT License
Classifier: Programming Language :: Python :: 3
Classifier: Programming Language :: Python :: 3.8
Classifier: Programming Language :: Python :: 3.9
Requires-Dist: pydantic (>=1.8.1,<2.0.0)
Requires-Dist: python-dotenv (>=0.15.0,<0.16.0)
Requires-Dist: python-slugify (>=4.0.1,<5.0.0)
Requires-Dist: pyzipper (>=0.3.4,<0.4.0)
Requires-Dist: requests (>=2.25.1,<3.0.0)
Requires-Dist: rich (>=9.13.0,<10.0.0)
Requires-Dist: toml (==0.10.2)
Requires-Dist: typer (>=0.3.2,<0.4.0)
Project-URL: Documentation, https://hay-kot.github.io/quick-zip-cli/
Project-URL: Repository, https://github.com/hay-kot/quick-zip-cli/
